setup.py
HandTracingModule/__init__.py
HandTrackModules.egg-info/PKG-INFO
HandTrackModules.egg-info/SOURCES.txt
HandTrackModules.egg-info/dependency_links.txt
HandTrackModules.egg-info/requires.txt
HandTrackModules.egg-info/top_level.txt