Metadata-Version: 1.0
Name: HandTrackModules
Version: 0.1.6
Summary: Useful tools to work with Hand Detection with cv2 and mediapipe
Home-page: https://github.com/joshuapaul2005/HandTrackingModule
Author: Joshua Paul
Author-email: joshblue2005@gmail.com
License: MIT
Keywords: cv2,mediapipe,Hand Track Module,Python 3
Platform: UNKNOWN
